.coveragerc
.dockerignore
.editorconfig
.travis-devel-requirements.txt
.travis-lowest-requirements.txt
.travis-release-requirements.txt
.travis.invenio.cfg
AUTHORS.rst
CHANGES.rst
LICENSE
MANIFEST.in
README.rst
RELEASE-NOTES.rst
pytest.ini
requirements-devel.txt
requirements-docs.txt
requirements.py
setup.py
tox.ini
docs/Makefile
docs/conf.py
docs/index.rst
invenio_matcher/__init__.py
invenio_matcher/api.py
invenio_matcher/config.py
invenio_matcher/core.py
invenio_matcher/engine.py
invenio_matcher/errors.py
invenio_matcher/models.py
invenio_matcher/registry.py
invenio_matcher/version.py
invenio_matcher.egg-info/PKG-INFO
invenio_matcher.egg-info/SOURCES.txt
invenio_matcher.egg-info/dependency_links.txt
invenio_matcher.egg-info/not-zip-safe
invenio_matcher.egg-info/requires.txt
invenio_matcher.egg-info/top_level.txt
invenio_matcher/matcherext/__init__.py
invenio_matcher/matcherext/engines/__init__.py
invenio_matcher/matcherext/engines/es.py
misc/header.py
misc/header.rst
tests/__init__.py
tests/helpers.py
tests/test_api.py
tests/test_core.py
tests/test_engine.py
tests/engines/helpers.py
tests/engines/test_es.py